nasharia_led_remote/__init__.py
nasharia_led_remote/commands.py
nasharia_led_remote/irsend.py
nasharia_led_remote-0.1.0.data/scripts/led-remote
nasharia_led_remote-0.1.0.dist-info/LICENSE
nasharia_led_remote-0.1.0.dist-info/METADATA
nasharia_led_remote-0.1.0.dist-info/WHEEL
nasharia_led_remote-0.1.0.dist-info/top_level.txt
nasharia_led_remote-0.1.0.dist-info/RECORD
